oxideshield/__init__.py
oxideshield/oxideshield.cpython-313-x86_64-linux-gnu.so
oxideshield/py.typed
oxideshield-0.1.4.dist-info/METADATA
oxideshield-0.1.4.dist-info/WHEEL
oxideshield-0.1.4.dist-info/licenses/LICENSE-COMMUNITY
oxideshield-0.1.4.dist-info/RECORD
