Metadata-Version: 2.4
Name: oxideshield
Version: 0.1.4
Classifier: Intended Audience :: Developers
Classifier: License :: OSI Approved :: Apache Software License
Classifier: Programming Language :: Python :: 3
Classifier: Programming Language :: Python :: 3.9
Classifier: Programming Language :: Python :: 3.10
Classifier: Programming Language :: Python :: 3.11
Classifier: Programming Language :: Python :: 3.12
Classifier: Programming Language :: Python :: 3.13
Classifier: Programming Language :: Python :: 3.14
Classifier: Programming Language :: Rust
Classifier: Topic :: Security
Classifier: Topic :: Scientific/Engineering :: Artificial Intelligence
Requires-Dist: pytest>=7.0 ; extra == 'dev'
Requires-Dist: pytest-asyncio>=0.21 ; extra == 'dev'
Requires-Dist: mypy>=1.0 ; extra == 'dev'
Requires-Dist: ruff>=0.1 ; extra == 'dev'
Provides-Extra: dev
License-File: LICENSE-COMMUNITY
Summary: High-performance LLM security toolkit
Keywords: llm,security,ai,red-team,guardrails
Author-email: Toasteez Limited <support@oxideshield.ai>
License: Apache-2.0
Requires-Python: >=3.9
Project-URL: Documentation, https://docs.oxideshield.ai
Project-URL: Homepage, https://oxideshield.ai
Project-URL: Issues, https://github.com/oxideshield/oxideshield/issues
Project-URL: Repository, https://github.com/oxideshield/oxideshield
